{
   "agent": "websock secure server",
   "behavior": "OK",
   "behaviorClose": "OK",
   "case": 26,
   "closedByMe": true,
   "createStats": true,
   "createWirelog": true,
   "description": "Send 10 Pings with payload.",
   "droppedByMe": false,
   "duration": 14,
   "expectation": "Pongs for our Pings with all the payloads. Note: This is not required by the Spec .. but we check for this behaviour anyway. Clean close with normal code.",
   "expected": {
      "OK": [
         [
            "pong",
            "payload-0"
         ],
         [
            "pong",
            "payload-1"
         ],
         [
            "pong",
            "payload-2"
         ],
         [
            "pong",
            "payload-3"
         ],
         [
            "pong",
            "payload-4"
         ],
         [
            "pong",
            "payload-5"
         ],
         [
            "pong",
            "payload-6"
         ],
         [
            "pong",
            "payload-7"
         ],
         [
            "pong",
            "payload-8"
         ],
         [
            "pong",
            "payload-9"
         ]
      ]
   },
   "expectedClose": {
      "closeCode": [
         1000
      ],
      "closedByMe": true,
      "requireClean": true
   },
   "failedByMe": false,
   "httpRequest": "GET /wss HTTP/1.1\r\nUser-Agent: AutobahnTestSuite/0.8.2-0.10.9\r\nHost: 127.0.0.1:8889\r\nUpgrade: WebSocket\r\nConnection: Upgrade\r\nPragma: no-cache\r\nCache-Control: no-cache\r\nSec-WebSocket-Key: kv5WoQDszWBeJwJZifUDHg==\r\nSec-WebSocket-Version: 13\r\n\r\n",
   "httpResponse": "HTTP/1.1 101 Switching Protocols\r\nDate: Wed, 18 May 2022 08:05:27 GMT\r\nUpgrade: websocket\r\nConnection: Upgrade\r\nSec-Websocket-Accept: xdRAWLeNR1syftzVO+JBPGRScJc=\r\n\r\n",
   "id": "2.10",
   "isServer": false,
   "localCloseCode": 1000,
   "localCloseReason": null,
   "received": [
      [
         "pong",
         "payload-0"
      ],
      [
         "pong",
         "payload-1"
      ],
      [
         "pong",
         "payload-2"
      ],
      [
         "pong",
         "payload-3"
      ],
      [
         "pong",
         "payload-4"
      ],
      [
         "pong",
         "payload-5"
      ],
      [
         "pong",
         "payload-6"
      ],
      [
         "pong",
         "payload-7"
      ],
      [
         "pong",
         "payload-8"
      ],
      [
         "pong",
         "payload-9"
      ]
   ],
   "remoteCloseCode": 1000,
   "remoteCloseReason": null,
   "reportCompressionRatio": false,
   "reportTime": false,
   "result": "Actual events match at least one expected.",
   "resultClose": "Connection was properly closed",
   "rxFrameStats": {
      "8": 1,
      "10": 10
   },
   "rxOctetStats": {
      "4": 1,
      "11": 10,
      "166": 1
   },
   "started": "2022-05-18T08:05:27.316Z",
   "trafficStats": null,
   "txFrameStats": {
      "8": 1,
      "9": 10
   },
   "txOctetStats": {
      "8": 1,
      "15": 10,
      "243": 1
   },
   "wasClean": true,
   "wasCloseHandshakeTimeout": false,
   "wasNotCleanReason": null,
   "wasOpenHandshakeTimeout": false,
   "wasServerConnectionDropTimeout": false,
   "wirelog": [
      [
         "TO",
         [
            243,
            "474554202f77737320485454502f312e310d0a557365722d4167656e743a204175746f6261686e5465737453756974652f302e382e322d302e31302e390d0a48 ..."
         ],
         false
      ],
      [
         "RO",
         [
            166,
            "485454502f312e312031303120537769746368696e672050726f746f636f6c730d0a446174653a205765642c203138204d617920323032322030383a30353a32 ..."
         ]
      ],
      [
         "TF",
         [
            9,
            "payload-0"
         ],
         9,
         true,
         0,
         "7f8d766e",
         null,
         null,
         false
      ],
      [
         "TO",
         [
            15,
            "89897f8d766e0fec0f0210ec12434f"
         ],
         false
      ],
      [
         "TF",
         [
            9,
            "payload-1"
         ],
         9,
         true,
         0,
         "0168f555",
         null,
         null,
         false
      ],
      [
         "TO",
         [
            15,
            "89890168f55571098c396e09917830"
         ],
         false
      ],
      [
         "TF",
         [
            9,
            "payload-2"
         ],
         9,
         true,
         0,
         "eafb8628",
         null,
         null,
         false
      ],
      [
         "TO",
         [
            15,
            "8989eafb86289a9aff44859ae205d8"
         ],
         false
      ],
      [
         "TF",
         [
            9,
            "payload-3"
         ],
         9,
         true,
         0,
         "b75badf7",
         null,
         null,
         false
      ],
      [
         "TO",
         [
            15,
            "8989b75badf7c73ad49bd83ac9da84"
         ],
         false
      ],
      [
         "TF",
         [
            9,
            "payload-4"
         ],
         9,
         true,
         0,
         "711a209d",
         null,
         null,
         false
      ],
      [
         "TO",
         [
            15,
            "8989711a209d017b59f11e7b44b045"
         ],
         false
      ],
      [
         "TF",
         [
            9,
            "payload-5"
         ],
         9,
         true,
         0,
         "4c06cc73",
         null,
         null,
         false
      ],
      [
         "TO",
         [
            15,
            "89894c06cc733c67b51f2367a85e79"
         ],
         false
      ],
      [
         "TF",
         [
            9,
            "payload-6"
         ],
         9,
         true,
         0,
         "3b3e2f79",
         null,
         null,
         false
      ],
      [
         "TO",
         [
            15,
            "89893b3e2f794b5f5615545f4b540d"
         ],
         false
      ],
      [
         "TF",
         [
            9,
            "payload-7"
         ],
         9,
         true,
         0,
         "73993e3f",
         null,
         null,
         false
      ],
      [
         "TO",
         [
            15,
            "898973993e3f03f847531cf85a1244"
         ],
         false
      ],
      [
         "TF",
         [
            9,
            "payload-8"
         ],
         9,
         true,
         0,
         "c2ced42f",
         null,
         null,
         false
      ],
      [
         "TO",
         [
            15,
            "8989c2ced42fb2afad43adafb002fa"
         ],
         false
      ],
      [
         "TF",
         [
            9,
            "payload-9"
         ],
         9,
         true,
         0,
         "d1328978",
         null,
         null,
         false
      ],
      [
         "TO",
         [
            15,
            "8989d1328978a153f014be53ed55e8"
         ],
         false
      ],
      [
         "TI",
         3
      ],
      [
         "RO",
         [
            11,
            "8a097061796c6f61642d30"
         ]
      ],
      [
         "RF",
         [
            9,
            "payload-0"
         ],
         10,
         true,
         0,
         false,
         null
      ],
      [
         "RO",
         [
            11,
            "8a097061796c6f61642d31"
         ]
      ],
      [
         "RF",
         [
            9,
            "payload-1"
         ],
         10,
         true,
         0,
         false,
         null
      ],
      [
         "RO",
         [
            11,
            "8a097061796c6f61642d32"
         ]
      ],
      [
         "RF",
         [
            9,
            "payload-2"
         ],
         10,
         true,
         0,
         false,
         null
      ],
      [
         "RO",
         [
            11,
            "8a097061796c6f61642d33"
         ]
      ],
      [
         "RF",
         [
            9,
            "payload-3"
         ],
         10,
         true,
         0,
         false,
         null
      ],
      [
         "RO",
         [
            11,
            "8a097061796c6f61642d34"
         ]
      ],
      [
         "RF",
         [
            9,
            "payload-4"
         ],
         10,
         true,
         0,
         false,
         null
      ],
      [
         "RO",
         [
            11,
            "8a097061796c6f61642d35"
         ]
      ],
      [
         "RF",
         [
            9,
            "payload-5"
         ],
         10,
         true,
         0,
         false,
         null
      ],
      [
         "RO",
         [
            11,
            "8a097061796c6f61642d36"
         ]
      ],
      [
         "RF",
         [
            9,
            "payload-6"
         ],
         10,
         true,
         0,
         false,
         null
      ],
      [
         "RO",
         [
            11,
            "8a097061796c6f61642d37"
         ]
      ],
      [
         "RF",
         [
            9,
            "payload-7"
         ],
         10,
         true,
         0,
         false,
         null
      ],
      [
         "RO",
         [
            11,
            "8a097061796c6f61642d38"
         ]
      ],
      [
         "RF",
         [
            9,
            "payload-8"
         ],
         10,
         true,
         0,
         false,
         null
      ],
      [
         "RO",
         [
            11,
            "8a097061796c6f61642d39"
         ]
      ],
      [
         "RF",
         [
            9,
            "payload-9"
         ],
         10,
         true,
         0,
         false,
         null
      ],
      [
         "TF",
         [
            2,
            "0x03e8"
         ],
         8,
         true,
         0,
         "b4aa2f52",
         null,
         null,
         false
      ],
      [
         "TO",
         [
            8,
            "8882b4aa2f52b742"
         ],
         false
      ],
      [
         "RO",
         [
            4,
            "880203e8"
         ]
      ],
      [
         "RF",
         [
            2,
            "0x03e8"
         ],
         8,
         true,
         0,
         false,
         null
      ]
   ]
}